base/__init__.py
base/base_components.py
components/__init__.py
components/creators.py
components/items.py
components/socialgraph.py
components/users.py
generators/__init__.py
generators/generators.py
metrics/__init__.py
metrics/measurement.py
models/__init__.py
models/bass.py
models/content.py
models/mf.py
models/popularity.py
models/random.py
models/recommender.py
models/social.py
trecs/__init__.py
trecs/base.py
trecs/generators.py
trecs/logging.py
trecs/matrix_ops.py
trecs/utils.py
trecs/validate.py
trecs/base/__init__.py
trecs/base/base_components.py
trecs/components/__init__.py
trecs/components/creators.py
trecs/components/items.py
trecs/components/socialgraph.py
trecs/components/users.py
trecs/metrics/__init__.py
trecs/metrics/measurement.py
trecs/models/__init__.py
trecs/models/bass.py
trecs/models/content.py
trecs/models/mf.py
trecs/models/popularity.py
trecs/models/random.py
trecs/models/recommender.py
trecs/models/social.py
trecs/random/__init__.py
trecs/random/generators.py
trecs-0.2.1.dist-info/LICENSE
trecs-0.2.1.dist-info/METADATA
trecs-0.2.1.dist-info/WHEEL
trecs-0.2.1.dist-info/top_level.txt
trecs-0.2.1.dist-info/RECORD
