Metadata-Version: 2.1
Name: trecs
Version: 0.2.1
Summary: Framework for simulating sociotechnical systems.
Home-page: https://github.com/elucherini/t-recs
Author: Eli Lucherini
Author-email: elucherini@cs.princeton.edu
License: MIT
Platform: UNKNOWN
Classifier: Programming Language :: Python :: 3
Classifier: License :: OSI Approved :: MIT License
Classifier: Operating System :: OS Independent
License-File: LICENSE
Requires-Dist: numpy (>=1.17.0)
Requires-Dist: scipy (>=1.4.1)
Requires-Dist: networkx (>=2.4)
Requires-Dist: tqdm (>=4.46.0)
Requires-Dist: lenskit (>=0.11.1)
Requires-Dist: pandas (==1.0.5)
